abstar/__init__.py
abstar/gl.py
abstar/pp.py
abstar/tl.py
abstar/version.py
abstar/annotation/__init__.py
abstar/annotation/annotator.py
abstar/annotation/antibody.py
abstar/annotation/germline.py
abstar/annotation/indels.py
abstar/annotation/mask.py
abstar/annotation/mutations.py
abstar/annotation/positions.py
abstar/annotation/productivity.py
abstar/annotation/regions.py
abstar/annotation/schema.py
abstar/annotation/umi.py
abstar/assigners/__init__.py
abstar/assigners/assigner.py
abstar/assigners/blastn.py
abstar/assigners/mmseqs.py
abstar/core/__init__.py
abstar/core/abstar.py
abstar/core/germline.py
abstar/germline_dbs/bcr/balbc/manifest.txt
abstar/germline_dbs/bcr/balbc/imgt_gapped/c.fasta
abstar/germline_dbs/bcr/balbc/imgt_gapped/d.fasta
abstar/germline_dbs/bcr/balbc/imgt_gapped/j.fasta
abstar/germline_dbs/bcr/balbc/imgt_gapped/v.fasta
abstar/germline_dbs/bcr/balbc/mmseqs/c
abstar/germline_dbs/bcr/balbc/mmseqs/c.dbtype
abstar/germline_dbs/bcr/balbc/mmseqs/c.index
abstar/germline_dbs/bcr/balbc/mmseqs/c.lookup
abstar/germline_dbs/bcr/balbc/mmseqs/c.source
abstar/germline_dbs/bcr/balbc/mmseqs/c_h
abstar/germline_dbs/bcr/balbc/mmseqs/c_h.dbtype
abstar/germline_dbs/bcr/balbc/mmseqs/c_h.index
abstar/germline_dbs/bcr/balbc/mmseqs/d
abstar/germline_dbs/bcr/balbc/mmseqs/d.dbtype
abstar/germline_dbs/bcr/balbc/mmseqs/d.index
abstar/germline_dbs/bcr/balbc/mmseqs/d.lookup
abstar/germline_dbs/bcr/balbc/mmseqs/d.source
abstar/germline_dbs/bcr/balbc/mmseqs/d_h
abstar/germline_dbs/bcr/balbc/mmseqs/d_h.dbtype
abstar/germline_dbs/bcr/balbc/mmseqs/d_h.index
abstar/germline_dbs/bcr/balbc/mmseqs/j
abstar/germline_dbs/bcr/balbc/mmseqs/j.dbtype
abstar/germline_dbs/bcr/balbc/mmseqs/j.index
abstar/germline_dbs/bcr/balbc/mmseqs/j.lookup
abstar/germline_dbs/bcr/balbc/mmseqs/j.source
abstar/germline_dbs/bcr/balbc/mmseqs/j_h
abstar/germline_dbs/bcr/balbc/mmseqs/j_h.dbtype
abstar/germline_dbs/bcr/balbc/mmseqs/j_h.index
abstar/germline_dbs/bcr/balbc/mmseqs/v
abstar-0.8.0.dist-info/licenses/LICENSE
abstar-0.8.0.dist-info/METADATA
abstar-0.8.0.dist-info/WHEEL
abstar-0.8.0.dist-info/entry_points.txt
abstar-0.8.0.dist-info/top_level.txt
abstar-0.8.0.dist-info/RECORD
