Metadata-Version: 2.4
Name: abstar
Version: 0.8.0
Summary: Germline assignment and annotation of AIRR data. Scalable from a single sequence to billions of sequences.
Author-email: Bryan Briney <briney@scripps.edu>
License: The MIT License (MIT)
Project-URL: Homepage, https://github.com/brineylab/abstar
Classifier: Development Status :: 5 - Production/Stable
Classifier: Intended Audience :: Science/Research
Classifier: License :: OSI Approved :: MIT License
Classifier: Operating System :: OS Independent
Classifier: Programming Language :: Python :: 3
Classifier: Programming Language :: Python :: 3.10
Classifier: Programming Language :: Python :: 3.11
Classifier: Programming Language :: Python :: 3.12
Classifier: Programming Language :: Python :: 3.13
Classifier: Topic :: Scientific/Engineering :: Bio-Informatics
Requires-Python: >=3.10
License-File: LICENSE
Requires-Dist: abutils>=0.5.1
Requires-Dist: click
Requires-Dist: matplotlib
Requires-Dist: numpy
Requires-Dist: pandas
Requires-Dist: parasail
Requires-Dist: polars
Requires-Dist: pyarrow
Requires-Dist: pytest
Dynamic: license-file
